rdstationpy/__init__.py
rdstationpy/api_client.py
rdstationpy/exceptions.py
rdstationpy/rdstation.py
rdstationpy/services/__init__.py
rdstationpy/services/activities.py
rdstationpy/services/campaigns.py
rdstationpy/services/contacts.py
rdstationpy/services/custom_fields.py
rdstationpy/services/deal_lost_reasons.py
rdstationpy/services/deal_pipelines.py
rdstationpy/services/deal_sources.py
rdstationpy/services/deals.py
rdstationpy/services/organizations.py
rdstationpy/services/products.py
rdstationpy/services/tasks.py
rdstationpy/services/teams.py
rdstationpy/services/users.py
rdstationpy/services/webhooks.py
rdstationpy/utils/config.py
rdstationpy-0.1.1.dist-info/METADATA
rdstationpy-0.1.1.dist-info/WHEEL
rdstationpy-0.1.1.dist-info/RECORD
